[
    {
        "bbox": [
            100.0,
            22.0,
            116.68571428571428,
            236.74285714285713
        ],
        "keypoints": [
            154.0,
            40.0,
            2,
            143.0,
            57.0,
            2,
            116.0,
            53.0,
            1,
            140.0,
            78.0,
            2,
            114.0,
            136.0,
            1,
            155.0,
            153.0,
            2,
            109.0,
            89.0,
            1,
            153.0,
            121.0,
            2,
            173.0,
            95.0,
            2,
            182.0,
            116.0,
            2
        ]
    },
    {
        "bbox": [
            58.51428571428571,
            3.657142857142857,
            65.82857142857142,
            168.22857142857157
        ],
        "keypoints": []
    },
    {
        "bbox": [
            550.4,
            50.285714285714285,
            66.74285714285715,
            127.08571428571429
        ],
        "keypoints": []
    }
]