[
    {
        "bbox": [
            399.5428571428572,
            82.28571428571429,
            99.65714285714282,
            130.74285714285713
        ],
        "keypoints": []
    },
    {
        "bbox": [
            429.71428571428567,
            154.51428571428573,
            162.74285714285722,
            153.60000000000005
        ],
        "keypoints": []
    },
    {
        "bbox": [
            532.8,
            105.82857142857142,
            56.22857142857143,
            122.05714285714282
        ],
        "keypoints": []
    }
]