[
    {
        "bbox": [
            361.0,
            114.0,
            108.0000000000001,
            107.00000000000001
        ],
        "keypoints": [
            429.0,
            155.0,
            2,
            409.0,
            149.0,
            2,
            456.2285714285714,
            143.54285714285714,
            2,
            375.7714285714286,
            143.54285714285714,
            2,
            434.74285714285713,
            213.94285714285715,
            2,
            388.57142857142856,
            215.77142857142857,
            2,
            463.54285714285714,
            191.54285714285714,
            2,
            369.3714285714286,
            206.17142857142858,
            2,
            440.6857142857143,
            221.25714285714287,
            1,
            400.0,
            227.2,
            1
        ]
    },
    {
        "bbox": [
            263.0,
            97.0,
            107.0,
            136.0
        ],
        "keypoints": [
            346.0,
            143.0,
            2,
            332.0,
            155.0,
            2,
            355.65714285714284,
            157.71428571428572,
            2,
            292.57142857142856,
            147.88571428571427,
            2,
            338.74285714285713,
            218.5142857142857,
            2,
            303.7714285714286,
            218.74285714285716,
            1,
            352.9142857142857,
            201.14285714285714,
            2,
            278.8571428571429,
            225.14285714285714,
            1,
            351.77142857142854,
            222.6285714285714,
            1,
            334.1714285714286,
            227.65714285714287,
            2
        ]
    },
    {
        "bbox": [
            195.0,
            182.0,
            135.05714285714285,
            298.0
        ],
        "keypoints": [
            274.0,
            221.0,
            2,
            260.0,
            242.0,
            2,
            227.0,
            244.99999999999997,
            2,
            286.0,
            294.0,
            2,
            209.0,
            369.0,
            2,
            256.9142857142857,
            405.0285714285714,
            2,
            203.0,
            338.0,
            2,
            245.0,
            386.0,
            2,
            273.8285714285714,
            324.1142857142857,
            1,
            300.0,
            355.0,
            2
        ]
    }
]