[
    {
        "bbox": [
            82.0,
            141.0,
            181.31428571428572,
            339.0
        ],
        "keypoints": [
            136.0,
            177.0,
            2,
            129.0,
            204.0,
            2,
            93.0,
            220.0,
            2,
            169.0,
            230.0,
            2,
            126.0,
            309.0,
            2,
            194.0,
            317.0,
            2,
            102.0,
            266.0,
            1,
            211.0,
            295.0,
            2,
            191.0,
            226.0,
            1,
            222.0,
            266.0,
            2
        ]
    },
    {
        "bbox": [
            382.0,
            211.0,
            118.11428571428566,
            269.0
        ],
        "keypoints": [
            435.0,
            252.0,
            2,
            439.0,
            281.0,
            2,
            405.0,
            306.0,
            2,
            484.0,
            271.0,
            2,
            411.0,
            387.0,
            2,
            479.0,
            356.0,
            2,
            395.0,
            370.0,
            2,
            491.0,
            321.0,
            2,
            409.0,
            357.0,
            1,
            485.0,
            326.0,
            1
        ]
    },
    {
        "bbox": [
            183.77142857142857,
            216.68571428571428,
            55.77142857142857,
            56.68571428571431
        ],
        "keypoints": []
    }
]