[
    {
        "bbox": [
            274.0,
            3.0,
            67.0,
            120.99999999999982
        ],
        "keypoints": [
            303.0,
            26.0,
            2,
            306.0,
            45.0,
            2,
            329.0,
            43.0,
            2,
            282.0,
            54.0,
            2,
            325.0,
            97.0,
            2,
            287.0,
            99.0,
            2,
            336.0,
            76.0,
            2,
            292.0,
            89.0,
            2,
            324.0,
            105.0,
            2,
            310.0,
            107.0,
            2
        ]
    },
    {
        "bbox": [
            347.0,
            3.0,
            67.99999999999994,
            77.00000000000001
        ],
        "keypoints": [
            381.0,
            17.0,
            2,
            382.0,
            35.0,
            2,
            401.0,
            31.000000000000004,
            2,
            364.0,
            40.0,
            2,
            398.0,
            59.0,
            1,
            370.0,
            67.0,
            1,
            409.0,
            57.0,
            2,
            356.0,
            65.0,
            2,
            396.0,
            59.0,
            1,
            371.0,
            65.0,
            1
        ]
    },
    {
        "bbox": [
            204.0,
            49.0,
            62.971428571428596,
            178.65714285714284
        ],
        "keypoints": [
            234.0,
            77.0,
            2,
            230.0,
            103.0,
            2,
            247.0,
            108.0,
            2,
            215.0,
            116.0,
            2,
            256.0,
            155.0,
            1,
            229.0,
            181.0,
            2,
            251.0,
            124.00000000000001,
            1,
            232.0,
            169.0,
            2,
            251.0,
            122.99999999999999,
            1,
            247.0,
            166.0,
            1
        ]
    },
    {
        "bbox": [
            416.0,
            0.0,
            74.05714285714285,
            62.171428571428564
        ],
        "keypoints": []
    },
    {
        "bbox": [
            221.25714285714284,
            26.97142857142857,
            53.48571428571429,
            91.88571428571429
        ],
        "keypoints": []
    },
    {
        "bbox": [
            288.9142857142857,
            140.8,
            84.11428571428571,
            63.99999999999997
        ],
        "keypoints": []
    }
]